psypher/__init__.py
psypher/cache.py
psypher/cipher.py
psypher/errors.py
psypher/scheme.py
psypher/secret.py
psypher-1.0.0.dist-info/LICENSE
psypher-1.0.0.dist-info/METADATA
psypher-1.0.0.dist-info/WHEEL
psypher-1.0.0.dist-info/top_level.txt
psypher-1.0.0.dist-info/RECORD
