Metadata-Version: 2.1
Name: psypher
Version: 1.0.0
Summary: A modern asymmetric encryption scheme.
Home-page: https://gitee.com/origamizyt/psypher
Author: origamizyt
Author-email: zhaoyitong18@163.com
License: UNKNOWN
Platform: UNKNOWN
Classifier: Programming Language :: Python :: 3
Classifier: License :: OSI Approved :: MIT License
Classifier: Operating System :: OS Independent
Requires-Python: >=3.6
Requires-Dist: cryptography
